Workbook
Name Slicer_Category: #N/A
Name Slicer_Order_Status: #N/A
Name Slicer_Payment_Method: #N/A
Name Slicer_Product: #N/A
Name Slicer_Region2: #N/A

Sheet Sheet1
A3: Order ID | B3: Customer | C3: Product | D3: Category | E3: Region | F3: Quantity | G3: Unit Price | H3: Sales | I3: Payment Method | J3: Order Status | K3: Order Date
A4: 5001 | B4: Ravi | C4: Laptop | D4: Electronics | E4: Hyderabad | F4: 1 | G4: 60000 | H4: 60000 | I4: UPI | J4: Delivered | K4: 46266
A5: 5002 | B5: Priya | C5: Mouse | D5: Accessories | E5: Chennai | F5: 5 | G5: 800 | H5: 4000 | I5: Card | J5: Delivered | K5: 46267
A6: 5003 | B6: Arjun | C6: Monitor | D6: Electronics | E6: Bengaluru | F6: 2 | G6: 20000 | H6: 40000 | I6: UPI | J6: Delivered | K6: 46268
A7: 5004 | B7: Sneha | C7: Keyboard | D7: Accessories | E7: Hyderabad | F7: 3 | G7: 1800 | H7: 5400 | I7: Cash | J7: Pending | K7: 46269
A8: 5005 | B8: Kiran | C8: Printer | D8: Office | E8: Chennai | F8: 1 | G8: 15000 | H8: 15000 | I8: UPI | J8: Delivered | K8: 46270
A9: 5006 | B9: Anjali | C9: Laptop | D9: Electronics | E9: Mumbai | F9: 2 | G9: 60000 | H9: 120000 | I9: Card | J9: Delivered | K9: 46271
A10: 5007 | B10: Rahul | C10: Headphones | D10: Accessories | E10: Hyderabad | F10: 4 | G10: 3000 | H10: 12000 | I10: UPI | J10: Cancelled | K10: 46272
A11: 5008 | B11: Divya | C11: Printer | D11: Office | E11: Bengaluru | F11: 2 | G11: 15000 | H11: 30000 | I11: Cash | J11: Delivered | K11: 46273
A12: 5009 | B12: Suresh | C12: Mouse | D12: Accessories | E12: Mumbai | F12: 10 | G12: 800 | H12: 8000 | I12: UPI | J12: Delivered | K12: 46274
A13: 5010 | B13: Meena | C13: Monitor | D13: Electronics | E13: Chennai | F13: 1 | G13: 20000 | H13: 20000 | I13: Card | J13: Pending | K13: 46275
A14: 5011 | B14: Vamsi | C14: Laptop | D14: Electronics | E14: Hyderabad | F14: 1 | G14: 60000 | H14: 60000 | I14: UPI | J14: Delivered | K14: 46276
A15: 5012 | B15: Pooja | C15: Keyboard | D15: Accessories | E15: Mumbai | F15: 4 | G15: 1800 | H15: 7200 | I15: Cash | J15: Delivered | K15: 46277
... A18: 5015 | B18: Varun | C18: Laptop | D18: Electronics | E18: Chennai | F18: 1 | G18: 60000 | H18: 60000 | I18: UPI | J18: Delivered | K18: 46280

Sheet Sheet7
B2: KPIS
A3: Sum of Sales | B3: Sum of Quantity | C3: Count of Order ID | D3: Average of Sales2
A4: 546600 | B4: 43 | C4: 15 | D4: 36440
A6: =GETPIVOTDATA("Sum of Sales",$A$3) -> 546600 | B6: =GETPIVOTDATA("Sum of Quantity",$A$3) -> 43 | C6: =GETPIVOTDATA("Count of Order ID",$A$3) -> 15 | D6: =GETPIVOTDATA("Average of Sales2",$A$3) -> 36440

Sheet Sheet8
A3: Order Date | B3: Sum of Sales
A4: 46266 | B4: 60000
A5: 46267 | B5: 4000
A6: 46268 | B6: 40000
A7: 46269 | B7: 5400
A8: 46270 | B8: 15000
A9: 46271 | B9: 120000
A10: 46272 | B10: 12000
A11: 46273 | B11: 30000
A12: 46274 | B12: 8000
A13: 46275 | B13: 20000
A14: 46276 | B14: 60000
A15: 46277 | B15: 7200
... A18: 46280 | B18: 60000
A19: Grand Total | B19: 546600

Sheet Sheet2
A1: Order ID | B1: Customer | C1: Product | D1: Category | E1: Region | F1: Quantity | G1: Unit Price | H1: Sales | I1: Payment Method | J1: Order Status | K1: Order Date | L1: Sales Category | M1: Quantity Category | N1: Priority Order
A2: 5001 | B2: Ravi | C2: Laptop | D2: Electronics | E2: Hyderabad | F2: 1 | G2: 60000 | H2: 60000 | I2: UPI | J2: Delivered | K2: 46266 | L2: =IF(H2>50000,"High Value","Normal") -> High Value | M2: =IF(F2>=5,"Bulk","Regular") -> Regular | N2: =IF(AND(H2>=50000,J2="Delivered"),"Priority","Normal") -> Priority
A3: 5002 | B3: Priya | C3: Mouse | D3: Accessories | E3: Chennai | F3: 5 | G3: 800 | H3: 4000 | I3: Card | J3: Delivered | K3: 46267 | L3: =IF(H3>50000,"High Value","Normal") -> Normal | M3: =IF(F3>=5,"Bulk","Regular") -> Bulk | N3: =IF(AND(H3>=50000,J3="Delivered"),"Priority","Normal") -> Normal
A4: 5003 | B4: Arjun | C4: Monitor | D4: Electronics | E4: Bengaluru | F4: 2 | G4: 20000 | H4: 40000 | I4: UPI | J4: Delivered | K4: 46268 | L4: =IF(H4>50000,"High Value","Normal") -> Normal | M4: =IF(F4>=5,"Bulk","Regular") -> Regular | N4: =IF(AND(H4>=50000,J4="Delivered"),"Priority","Normal") -> Normal
A5: 5004 | B5: Sneha | C5: Keyboard | D5: Accessories | E5: Hyderabad | F5: 3 | G5: 1800 | H5: 5400 | I5: Cash | J5: Pending | K5: 46269 | L5: =IF(H5>50000,"High Value","Normal") -> Normal | M5: =IF(F5>=5,"Bulk","Regular") -> Regular | N5: =IF(AND(H5>=50000,J5="Delivered"),"Priority","Normal") -> Normal
A6: 5005 | B6: Kiran | C6: Printer | D6: Office | E6: Chennai | F6: 1 | G6: 15000 | H6: 15000 | I6: UPI | J6: Delivered | K6: 46270 | L6: =IF(H6>50000,"High Value","Normal") -> Normal | M6: =IF(F6>=5,"Bulk","Regular") -> Regular | N6: =IF(AND(H6>=50000,J6="Delivered"),"Priority","Normal") -> Normal
A7: 5006 | B7: Anjali | C7: Laptop | D7: Electronics | E7: Mumbai | F7: 2 | G7: 60000 | H7: 120000 | I7: Card | J7: Delivered | K7: 46271 | L7: =IF(H7>50000,"High Value","Normal") -> High Value | M7: =IF(F7>=5,"Bulk","Regular") -> Regular | N7: =IF(AND(H7>=50000,J7="Delivered"),"Priority","Normal") -> Priority
A8: 5007 | B8: Rahul | C8: Headphones | D8: Accessories | E8: Hyderabad | F8: 4 | G8: 3000 | H8: 12000 | I8: UPI | J8: Cancelled | K8: 46272 | L8: =IF(H8>50000,"High Value","Normal") -> Normal | M8: =IF(F8>=5,"Bulk","Regular") -> Regular | N8: =IF(AND(H8>=50000,J8="Delivered"),"Priority","Normal") -> Normal
A9: 5008 | B9: Divya | C9: Printer | D9: Office | E9: Bengaluru | F9: 2 | G9: 15000 | H9: 30000 | I9: Cash | J9: Delivered | K9: 46273 | L9: =IF(H9>50000,"High Value","Normal") -> Normal | M9: =IF(F9>=5,"Bulk","Regular") -> Regular | N9: =IF(AND(H9>=50000,J9="Delivered"),"Priority","Normal") -> Normal
A10: 5009 | B10: Suresh | C10: Mouse | D10: Accessories | E10: Mumbai | F10: 10 | G10: 800 | H10: 8000 | I10: UPI | J10: Delivered | K10: 46274 | L10: =IF(H10>50000,"High Value","Normal") -> Normal | M10: =IF(F10>=5,"Bulk","Regular") -> Bulk | N10: =IF(AND(H10>=50000,J10="Delivered"),"Priority","Normal") -> Normal
A11: 5010 | B11: Meena | C11: Monitor | D11: Electronics | E11: Chennai | F11: 1 | G11: 20000 | H11: 20000 | I11: Card | J11: Pending | K11: 46275 | L11: =IF(H11>50000,"High Value","Normal") -> Normal | M11: =IF(F11>=5,"Bulk","Regular") -> Regular | N11: =IF(AND(H11>=50000,J11="Delivered"),"Priority","Normal") -> Normal
A12: 5011 | B12: Vamsi | C12: Laptop | D12: Electronics | E12: Hyderabad | F12: 1 | G12: 60000 | H12: 60000 | I12: UPI | J12: Delivered | K12: 46276 | L12: =IF(H12>50000,"High Value","Normal") -> High Value | M12: =IF(F12>=5,"Bulk","Regular") -> Regular | N12: =IF(AND(H12>=50000,J12="Delivered"),"Priority","Normal") -> Priority
A13: 5012 | B13: Pooja | C13: Keyboard | D13: Accessories | E13: Mumbai | F13: 4 | G13: 1800 | H13: 7200 | I13: Cash | J13: Delivered | K13: 46277 | L13: =IF(H13>50000,"High Value","Normal") -> Normal | M13: =IF(F13>=5,"Bulk","Regular") -> Regular | N13: =IF(AND(H13>=50000,J13="Delivered"),"Priority","Normal") -> Normal
... A16: 5015 | B16: Varun | C16: Laptop | D16: Electronics | E16: Chennai | F16: 1 | G16: 60000 | H16: 60000 | I16: UPI | J16: Delivered | K16: 46280 | L16: =IF(H16>50000,"High Value","Normal") -> High Value | M16: =IF(F16>=5,"Bulk","Regular") -> Regular | N16: =IF(AND(H16>=50000,J16="Delivered"),"Priority","Normal") -> Priority
H19: 546600
G23: Order Date | H23: Sales
G24: 46266 | H24: 60000
G25: 46267 | H25: 4000
G26: 46268 | H26: 40000
G27: 46269 | H27: 5400
G28: 46270 | H28: 15000
G29: 46271 | H29: 120000
G30: 46272 | H30: 12000
G31: 46273 | H31: 30000
G32: 46274 | H32: 8000
G33: 46275 | H33: 20000
G34: 46276 | H34: 60000
G35: 46277 | H35: 7200
... G38: 46280 | H38: 60000

Sheet Sheet3
A1: RETAIL SALES ANALYSIS CALCULATIONS
A3: TOTAL SALES | B3: =SUM(Sheet2!H2:H16) -> 546600
A4: TOTAL ORDERS | B4: =COUNT(Sheet2!A2:A16) -> 15
A5: TOTAL QUANTITY | B5: =SUM(Sheet2!F2:F16) -> 43
A6: HIGHEST SALE | B6: =MAX(Sheet2!H2:H16) -> 120000
A7: LOWEST SALE | B7: =MIN(Sheet2!H2:H16) -> 4000
A8: AVERAGE SALE | B8: =AVERAGE(Sheet2!H2:H16) -> 36440
A10: LAPTOP SALES | B10: =SUMIF(Sheet2!C2:C16,"Laptop",Sheet2!H2:H16) -> 300000
A11: HYDERABAD SALES | B11: =SUMIF(Sheet2!E2:E16,"Hyderabad",Sheet2!H2:H16) -> 182400
A12: LAPTOP SALES IN HYDERABAD | B12: =SUMIFS(Sheet2!H2:H16,Sheet2!C2:C16,"Laptop",Sheet2!E2:E16,"Hyderabad") -> 120000
A13: DELIVERED ORDERS | B13: =COUNTIF(Sheet2!J2:J16,"Delivered") -> 12
A14: PENDING ORDERS | B14: =COUNTIF(Sheet2!J2:J16,"Pending") -> 2
A15: CANCELLED ORDERS | B15: =COUNTIF(Sheet2!J2:J16,"Cancelled") -> 1
A16: DELIVERED SALES | B16: =SUMIF(Sheet2!J2:J16,"Delivered",Sheet2!H2:H16) -> 509200
A17: ELECTRONICS SALES | B17: =SUMIF(Sheet2!D2:D16,"Electronics",Sheet2!H2:H16) -> 420000
A18: ACCESSORIES SALES | B18: =SUMIF(Sheet2!D2:D16,"Accessories",Sheet2!H2:H16) -> 36600
A19: OFFICE SALES | B19: =SUMIF(Sheet2!D2:D16,"Office",Sheet2!H2:H16) -> 90000

Sheet Sheet4
A1: Row Labels | B1: Sum of Sales | D1: Row Labels | E1: Sum of Quantity | G1: Row Labels | H1: Sum of Sales | J1: Row Labels | K1: Count of Order ID | M1: Row Labels | N1: Count of Order ID | Z1: Row Labels | AA1: Sum of Sales
A2: Headphones | B2: 12000 | D2: Headphones | E2: 4 | G2: Bengaluru | H2: 130000 | J2: Card | K2: 4 | M2: Cancelled | N2: 1 | Z2: 46266 | AA2: 60000
A3: Keyboard | B3: 12600 | D3: Keyboard | E3: 7 | G3: Chennai | H3: 99000 | J3: Cash | K3: 3 | M3: Delivered | N3: 12 | Z3: 46267 | AA3: 4000
A4: Laptop | B4: 300000 | D4: Laptop | E4: 5 | G4: Hyderabad | H4: 182400 | J4: UPI | K4: 8 | M4: Pending | N4: 2 | Z4: 46268 | AA4: 40000
A5: Monitor | B5: 120000 | D5: Monitor | E5: 6 | G5: Mumbai | H5: 135200 | J5: Grand Total | K5: 15 | M5: Grand Total | N5: 15 | Z5: 46269 | AA5: 5400
A6: Mouse | B6: 12000 | D6: Mouse | E6: 15 | G6: Grand Total | H6: 546600 | Z6: 46270 | AA6: 15000
A7: Printer | B7: 90000 | D7: Printer | E7: 6 | Z7: 46271 | AA7: 120000
A8: Grand Total | B8: 546600 | D8: Grand Total | E8: 43 | Z8: 46272 | AA8: 12000
Z9: 46273 | AA9: 30000
Z10: 46274 | AA10: 8000
Z11: 46275 | AA11: 20000
Z12: 46276 | AA12: 60000
Z13: 46277 | AA13: 7200
Z14: 46278 | AA14: 45000
Z15: 46279 | AA15: 60000
Z16: 46280 | AA16: 60000
Z17: Grand Total | AA17: 546600

Sheet Sheet5
B2: RETAIL SALES PERFORMANCE DASHBOARD
B5: TOTAL SALES | E5: TOTAL ORDERS | H5: TOTAL QUANTITY | K5: HIGHEST SALE
B7: =Sheet3!B3 -> 546600 | E7: =Sheet3!B4 -> 15 | H7: =Sheet3!B5 -> 43 | K7: =Sheet3!B6 -> 120000

Sheet Sheet6
